{
  "environmentId": "practicum-env-marina-bugfix-39884b",
  "namespace": "practicum-tks",
  "state": "Rejected",
  "reason": "Gitea PUT /contents/gitops/environments/practicum/self-service/generated/kustomization.yaml: 500 {\"message\":\"\",\"url\":\"http://gitea-practicum.d8case.ru/api/swagger\"}\n",
  "owner": "marina-volkova-practicum",
  "profile": "app-with-postgres-vm",
  "postgresVersion": "17",
  "activeEnvironments": 2,
  "activeVirtualMachines": 2,
  "expiresAt": "2026-06-10T11:13:41Z",
  "updatedAt": "2026-06-10T07:24:01Z"
}
